esa/ApiClient.py
esa/Chains.py
esa/DBConnection.py
esa/Defaults.py
esa/Embedding.py
esa/Extensions.py
esa/GpuCheck.py
esa/Interactions.py
esa/Memories.py
esa/Models.py
esa/Providers.py
esa/Websearch.py
esa/__init__.py
esa/app.py
esa_ai-1.4.23.dist-info/LICENSE
esa_ai-1.4.23.dist-info/METADATA
esa_ai-1.4.23.dist-info/WHEEL
esa_ai-1.4.23.dist-info/top_level.txt
esa_ai-1.4.23.dist-info/RECORD
