Metadata-Version: 2.1
Name: esa-ai
Version: 1.4.23
Summary: An Artificial Intelligence Automation Platform. AI Instruction management from various providers, has an adaptive memory, and a versatile plugin system with many commands including web browsing. Supports many AI providers and models and growing support every day.
Author: Michael Cloutier
Author-email: michael.cloutier@experian.com
Requires-Python: >=3.10
License-File: LICENSE
Requires-Dist: esa-python-sdk ==0.0.30
Requires-Dist: safeexecute ==0.0.6
Requires-Dist: g4f ==0.1.7.2
Requires-Dist: esa-local-llm ==0.0.15
Requires-Dist: google-generativeai ==0.2.1
Requires-Dist: discord ==2.3.2
Requires-Dist: anthropic ==0.4.1
Requires-Dist: arxiv ==1.4.8
Requires-Dist: PyGithub ==2.1.1
Requires-Dist: hugchat ==0.3.7
Requires-Dist: bardapi ==0.1.38
Requires-Dist: whisper-cpp-pybind ==0.1.2
Requires-Dist: mysql-connector-python ==8.1.0
Requires-Dist: pydub ==0.25.1
